nirman/__init__.py
nirman/builder.py
nirman/cli.py
nirman/parser.py
nirman_cli-0.1.9.dist-info/licenses/LICENSE
nirman_cli-0.1.9.dist-info/METADATA
nirman_cli-0.1.9.dist-info/WHEEL
nirman_cli-0.1.9.dist-info/entry_points.txt
nirman_cli-0.1.9.dist-info/top_level.txt
nirman_cli-0.1.9.dist-info/RECORD
