Metadata-Version: 2.4
Name: Nirman-cli
Version: 0.1.9
Summary: A CLI tool to create project folder structures from a markdown file.
Author-email: Hemanth Reddy Annem <Hemanthreddyannem@gmail.com>
License: MIT License
Project-URL: Homepage, https://github.com/Hemanth0411/Nirman-cli
Project-URL: Repository, https://github.com/Hemanth0411/Nirman-cli
Project-URL: Bug Tracker, https://github.com/Hemanth0411/Nirman-cli/issues
Keywords: cli,scaffolding,project-structure,markdown
Classifier: Development Status :: 4 - Beta
Classifier: Intended Audience :: Developers
Classifier: License :: OSI Approved :: MIT License
Classifier: Operating System :: OS Independent
Classifier: Programming Language :: Python :: 3
Classifier: Programming Language :: Python :: 3.7
Classifier: Programming Language :: Python :: 3.8
Classifier: Programming Language :: Python :: 3.9
Classifier: Programming Language :: Python :: 3.10
Classifier: Programming Language :: Python :: 3.11
Classifier: Programming Language :: Python :: 3.12
Classifier: Topic :: Software Development :: Build Tools
Classifier: Topic :: Utilities
Requires-Python: >=3.7
License-File: LICENSE
Dynamic: license-file
